[{"use":"jd_5bb16d6462414","code":"S5KkcRUxL9FKDJh7ylvMLcA"},{"use":"jd_7399bee01a89e","code":"S5KkcRx0Q_AaCdRr1xf8DIQ"},{"use":"15022052312_p","code":"Sv_hzQhwZ8FbUIRib1A"},{"use":"jd_6e0cd5023b791","code":"S5KkcRksZpgDSIBj3xvADdQ"},{"use":"13536765947_p","code":"Sv_52Qxge81HeJB2b1A"},{"use":"jd_LyVyYIZjfyOm","code":"S5KkcPFd_vD2uSkCi3YhX"},{"use":"jd_pLRuHlGvjpKZ","code":"S5KkcAGJ7sCyLV1yu1Ixg"},{"use":"jd_4130ddb669e89","code":"S5KkcRB8a9QCDchzynaICfQ"},{"use":"65471743-763539","code":"SuPh3Rx8e8VfKJxz3kfQD"}]
