[{"user":"jd_5bb16d6462414","rewardRecordId":326731619,"completed":true,"rewardOk":false},{"user":"jd_7399bee01a89e","rewardRecordId":326732086,"completed":true,"rewardOk":false},{"user":"15022052312_p","rewardRecordId":326732545,"completed":true,"rewardOk":false},{"user":"jd_6e0cd5023b791","rewardRecordId":326733013,"completed":true,"rewardOk":false},{"user":"13536765947_p","rewardRecordId":326733406,"completed":true,"rewardOk":false},{"user":"jd_LyVyYIZjfyOm","rewardRecordId":326734010,"completed":true,"rewardOk":false},{"user":"jd_pLRuHlGvjpKZ","rewardRecordId":326734416,"completed":true,"rewardOk":false}]