[{"user":"jd_5bb16d6462414","rewardRecordId":315633293,"completed":false,"rewardOk":false},{"user":"jd_7399bee01a89e","rewardRecordId":315634541,"completed":false,"rewardOk":false},{"user":"15022052312_p","rewardRecordId":315635513,"completed":false,"rewardOk":false},{"user":"jd_6e0cd5023b791","rewardRecordId":315636253,"completed":false,"rewardOk":false},{"user":"13536765947_p","rewardRecordId":315636876,"completed":false,"rewardOk":false},{"user":"jd_LyVyYIZjfyOm","rewardRecordId":315637588,"completed":false,"rewardOk":false},{"user":"jd_pLRuHlGvjpKZ","rewardRecordId":315637947,"completed":false,"rewardOk":false},{"user":"jd_4130ddb669e89","rewardRecordId":315638321,"completed":false,"rewardOk":false},{"user":"65471743-763539","rewardRecordId":315638646,"completed":false,"rewardOk":false}]